mcp_judge/__init__.py
mcp_judge/app.py
mcp_judge/main.py
mcp_judge-0.1.4.dist-info/METADATA
mcp_judge-0.1.4.dist-info/WHEEL
mcp_judge-0.1.4.dist-info/entry_points.txt
mcp_judge-0.1.4.dist-info/top_level.txt
mcp_judge-0.1.4.dist-info/RECORD
