Metadata-Version: 2.4
Name: mcp-judge
Version: 0.1.4
Summary: An interactive application for testing MCP tools.
Home-page: https://github.com/NilavoBoral/mcp-judge
Author: Nilavo Boral
Author-email: nilavoboral@gmail.com
Project-URL: LinkedIn, https://www.linkedin.com/in/nilavo-boral-123bb5228/
Classifier: Programming Language :: Python :: 3.11
Classifier: License :: OSI Approved :: MIT License
Classifier: Operating System :: OS Independent
Requires-Python: >=3.11
Requires-Dist: streamlit==1.49.1
Requires-Dist: fastmcp==2.12.3
Dynamic: author
Dynamic: author-email
Dynamic: classifier
Dynamic: description
Dynamic: description-content-type
Dynamic: home-page
Dynamic: project-url
Dynamic: requires-dist
Dynamic: requires-python
Dynamic: summary
